relay_tunnel/__init__.py
relay_tunnel/__main__.py
relay_tunnel/http.py
relay_tunnel/irc.py
relay_tunnel/utils.py
relay_tunnel/websocket.py
tests/__init__.py
tests/test_http_relay_tunnel.py
tests/test_websocket_relay_tunnel.py
tests/util.py
relay_tunnel-0.3.2.dist-info/METADATA
relay_tunnel-0.3.2.dist-info/WHEEL
relay_tunnel-0.3.2.dist-info/entry_points.txt
relay_tunnel-0.3.2.dist-info/top_level.txt
relay_tunnel-0.3.2.dist-info/RECORD
