Metadata-Version: 2.1
Name: relay-tunnel
Version: 0.3.2
Summary: WebSocket relay tunnel plugin for turbo-tunnel.
Home-page: https://github.com/turbo-tunnel/relay-tunnel
Author: drunkdream
Author-email: drunkdream@qq.com
License: MIT
Platform: UNKNOWN
Classifier: Development Status :: 3 - Alpha
Classifier: License :: OSI Approved :: MIT License
Classifier: Programming Language :: Python
Classifier: Programming Language :: Python :: 3
Classifier: Programming Language :: Python :: 3.5
Classifier: Programming Language :: Python :: 3.6
Classifier: Programming Language :: Python :: 3.7
Classifier: Programming Language :: Python :: 3.8
Classifier: Intended Audience :: Developers
Requires-Python: >=3.5
Requires-Dist: turbo-tunnel
